animation/__init__.py
animation/animator.py
animation/easing.py
animation/transitions.py
components/__init__.py
components/basic.py
components/display.py
components/layout.py
core/__init__.py
core/application.py
core/component.py
core/context.py
core/events.py
core/renderer.py
core/window.py
examples/__init__.py
examples/animation_example.py
examples/basic_example.py
examples/complete_example.py
examples/layout_example.py
examples/simple_test.py
examples/visualization_example.py
styling/__init__.py
styling/parser.py
styling/styles.py
styling/utilities.py
visualization/__init__.py
visualization/charts.py
visualization/data_table.py
visualization/plots.py
pulse_ui-1.0.0.dist-info/METADATA
pulse_ui-1.0.0.dist-info/WHEEL
pulse_ui-1.0.0.dist-info/entry_points.txt
pulse_ui-1.0.0.dist-info/top_level.txt
pulse_ui-1.0.0.dist-info/RECORD
