Metadata-Version: 2.4
Name: pulse-ui
Version: 1.0.0
Summary: A modern Python GUI library with React-like components and utility-first styling.
Home-page: https://github.com/tikipiya/PulseUI
Author: tikisan
Author-email: s2501082@sendai-nct.jp
Classifier: Development Status :: 3 - Alpha
Classifier: Intended Audience :: Developers
Classifier: License :: OSI Approved :: MIT License
Classifier: Operating System :: OS Independent
Classifier: Programming Language :: Python :: 3
Classifier: Programming Language :: Python :: 3.10
Classifier: Programming Language :: Python :: 3.11
Classifier: Programming Language :: Python :: 3.12
Classifier: Topic :: Software Development :: Libraries :: Python Modules
Classifier: Topic :: Software Development :: User Interfaces
Requires-Python: >=3.10
Requires-Dist: PyOpenGL>=3.1.0
Requires-Dist: PyOpenGL-accelerate>=3.1.0
Requires-Dist: pygame>=2.1.0
Requires-Dist: numpy>=1.21.0
Requires-Dist: Pillow>=9.0.0
Requires-Dist: moderngl>=5.6.0
Requires-Dist: pyrr>=0.10.0
Requires-Dist: glfw>=2.5.0
Requires-Dist: freetype-py>=2.3.0
Provides-Extra: dev
Requires-Dist: pytest>=6.0; extra == "dev"
Requires-Dist: black>=22.0; extra == "dev"
Requires-Dist: flake8>=4.0; extra == "dev"
Requires-Dist: mypy>=0.910; extra == "dev"
Provides-Extra: docs
Requires-Dist: sphinx>=4.0; extra == "docs"
Requires-Dist: sphinx-rtd-theme>=1.0; extra == "docs"
Dynamic: author
Dynamic: author-email
Dynamic: classifier
Dynamic: description
Dynamic: description-content-type
Dynamic: home-page
Dynamic: provides-extra
Dynamic: requires-dist
Dynamic: requires-python
Dynamic: summary
